srf_client/__init__.py
srf_client/chargers.py
srf_client/client.py
srf_client/filter.py
srf_client/fleets.py
srf_client/legs.py
srf_client/locations.py
srf_client/model.py
srf_client/oauth.py
srf_client/orders.py
srf_client/organisations.py
srf_client/paging.py
srf_client/pandas.py
srf_client/routes.py
srf_client/sort.py
srf_client/trailers.py
srf_client/transactions.py
srf_client/trials.py
srf_client/trips.py
srf_client/util.py
srf_client/vehicle_classes.py
srf_client/vehicles.py
srf_client-2.9.dist-info/LICENSE
srf_client-2.9.dist-info/METADATA
srf_client-2.9.dist-info/WHEEL
srf_client-2.9.dist-info/top_level.txt
srf_client-2.9.dist-info/RECORD
