Metadata-Version: 2.1
Name: srf-client
Version: 2.9
Summary: Centre for Sustainable Road Freight - Data Platform client
Author-email: James Howe <jmh205@cam.ac.uk>
Maintainer-email: Centre for Sustainable Road Freight <tech@csrf.ac.uk>
License: MIT License
Project-URL: Homepage, https://data.csrf.ac.uk
Project-URL: Documentation, https://data.csrf.ac.uk/python/docs
Classifier: Development Status :: 4 - Beta
Classifier: License :: OSI Approved :: MIT License
Classifier: Programming Language :: Python :: 3
Classifier: Programming Language :: Python :: 3.8
Classifier: Programming Language :: Python :: 3.9
Classifier: Programming Language :: Python :: 3.10
Classifier: Programming Language :: Python :: 3.11
Classifier: Programming Language :: Python :: 3.12
Classifier: Programming Language :: Python :: 3.13
Classifier: Programming Language :: Python :: 3.14
Classifier: Programming Language :: Python :: Implementation :: CPython
Classifier: Programming Language :: Python :: Implementation :: GraalPy
Classifier: Programming Language :: Python :: Implementation :: PyPy
Classifier: Operating System :: OS Independent
Classifier: Environment :: Console
Classifier: Environment :: Web Environment
Classifier: Intended Audience :: Developers
Classifier: Intended Audience :: Science/Research
Classifier: Topic :: Scientific/Engineering
Classifier: Natural Language :: English
Requires-Python: >=3.8
License-File: LICENSE
Requires-Dist: attrs>=20.1.0
Requires-Dist: CacheControl
Requires-Dist: geopy<3
Requires-Dist: immutabledict<3
Requires-Dist: lazy-object-proxy~=1.4
Requires-Dist: pyhumps<4,>=1.6
Requires-Dist: requests~=2.22
Requires-Dist: iso8601; python_version < "3.11"
Provides-Extra: dev
Requires-Dist: coverage[toml]~=7.0; extra == "dev"
Requires-Dist: flake8~=7.0; extra == "dev"
Requires-Dist: flake8-docstrings~=1.0; extra == "dev"
Requires-Dist: flake8-pyproject~=1.0; extra == "dev"
Requires-Dist: pydocstyle~=6.1; extra == "dev"
Requires-Dist: pytest~=7.2; extra == "dev"
Requires-Dist: pytest-cov~=4.0; extra == "dev"
Requires-Dist: pytest-mock~=3.0; extra == "dev"
Requires-Dist: requests-mock<2,>=1.9.2; extra == "dev"
Requires-Dist: requests-oauthlib~=2.0; extra == "dev"
Provides-Extra: oauth
Requires-Dist: requests-oauthlib~=2.0; extra == "oauth"
Provides-Extra: pandas
Requires-Dist: pandas<3,>=1.2; extra == "pandas"
